[
  {
    "calendarInfo": {
      "dates": {
        "bs": {
          "year": {
            "np": "२०२७",
            "en": "2027"
          },
          "month": {
            "np": "भाद्र",
            "code": {
              "np": "५",
              "en": "5"
            },
            "en": "Bhadra"
          },
          "day": {
            "np": "१",
            "en": "1"
          },
          "full": {
            "np": "२०२७-५-१",
            "en": "2027-5-1"
          }
        },
        "ad": {
          "year": {
            "np": "१९७०",
            "en": "1970"
          },
          "month": {
            "np": null,
            "code": {
              "np": null,
              "en": "8"
            },
            "en": "August"
          },
          "day": {
            "np": "१७",
            "en": "17"
          },
          "full": {
            "np": "१९७०-०८-१७",
            "en": "1970-8-17"
          }
        }
      },
      "days": {
        "dayOfWeek": {
          "np": "सोमवार",
          "en": "Monday"
        },
        "codes": {
          "np": null,
          "en": "2"
        }
      },
      "nepaliEra": {
        "sakSambat": {
          "np": null,
          "en": null
        },
        "nepalSambat": {
          "year": {
            "np": "१०९०",
            "en": "1090"
          },
          "month": {
            "np": null,
            "code": {
              "np": null,
              "en": null
            },
            "en": null
          }
        }
      }
    },
    "tithiDetails": null,
    "panchangaDetails": null,
    "hrituDetails": null,
    "auspiciousMoments": {
      "sahits": [],
      "muhurats": []
    },
    "eventDetails": [
      {
        "id": 5,
        "category": {
          "name": "Other",
          "id": 124264
        },
        "displayType": "Calendar Event",
        "title": {
          "np": "श्रि शिव-पवित्र रोपण",
          "en": "Shree Shivashya Pabitraropan"
        },
        "isHoliday": false,
        "location": null,
        "timing": {
          "from": null,
          "to": null
        },
        "details": {
          "en": null,
          "np": null
        }
      },
      {
        "id": 5,
        "category": {
          "name": "Other",
          "id": 124416
        },
        "displayType": "Calendar Event",
        "title": {
          "np": "जनै पुर्णिमा",
          "en": "Rishitarpani (Janai Purnima)"
        },
        "isHoliday": false,
        "location": null,
        "timing": {
          "from": null,
          "to": null
        },
        "details": {
          "en": null,
          "np": null
        }
      },
      {
        "id": 5,
        "category": {
          "name": "Other",
          "id": 124419
        },
        "displayType": "Calendar Event",
        "title": {
          "np": "हयग्रीवोत्पत्ति",
          "en": "Hayagriwotpatti:"
        },
        "isHoliday": false,
        "location": null,
        "timing": {
          "from": null,
          "to": null
        },
        "details": {
          "en": null,
          "np": null
        }
      },
      {
        "id": 5,
        "category": {
          "name": "Other",
          "id": 124441
        },
        "displayType": "Calendar Event",
        "title": {
          "np": "भाद्र संक्रान्ति",
          "en": "Bhadra Sankranti"
        },
        "isHoliday": false,
        "location": null,
        "timing": {
          "from": null,
          "to": null
        },
        "details": {
          "en": null,
          "np": null
        }
      },
      {
        "id": 5,
        "category": {
          "name": "others",
          "id": 314668
        },
        "displayType": "Calendar Event",
        "title": {
          "np": "कीर्तिपुरमा बाघभैरव यात्रा",
          "en": "Kirtipur Baagbhairab Jaatra"
        },
        "isHoliday": false,
        "location": null,
        "timing": {
          "from": null,
          "to": null
        },
        "details": {
          "en": null,
          "np": null
        }
      },
      {
        "id": 6034,
        "category": {
          "name": "others",
          "id": 463031
        },
        "displayType": "Calendar Event",
        "title": {
          "np": "पुर्णिमा व्रत",
          "en": "Purnima Brata"
        },
        "isHoliday": false,
        "location": null,
        "timing": {
          "from": null,
          "to": null
        },
        "details": {
          "en": null,
          "np": null
        }
      }
    ]
  },
  {
    "calendarInfo": {
      "dates": {
        "bs": {
          "year": {
            "np": "२०२७",
            "en": "2027"
          },
          "month": {
            "np": "भाद्र",
            "code": {
              "np": "५",
              "en": "5"
            },
            "en": "Bhadra"
          },
          "day": {
            "np": "२",
            "en": "2"
          },
          "full": {
            "np": "२०२७-५-२",
            "en": "2027-5-2"
          }
        },
        "ad": {
          "year": {
            "np": "१९७०",
            "en": "1970"
          },
          "month": {
            "np": null,
            "code": {
              "np": null,
              "en": "8"
            },
            "en": "August"
          },
          "day": {
            "np": "१८",
            "en": "18"
          },
          "full": {
            "np": "१९७०-०८-१८",
            "en": "1970-8-18"
          }
        }
      },
      "days": {
        "dayOfWeek": {
          "np": "मङ्गलवार",
          "en": "Tuesday"
        },
        "codes": {
          "np": null,
          "en": "3"
        }
      },
      "nepaliEra": {
        "sakSambat": {
          "np": null,
          "en": null
        },
        "nepalSambat": {
          "year": {
            "np": "१०९०",
            "en": "1090"
          },
          "month": {
            "np": null,
            "code": {
              "np": null,
              "en": null
            },
            "en": null
          }
        }
      }
    },
    "tithiDetails": null,
    "panchangaDetails": null,
    "hrituDetails": null,
    "auspiciousMoments": {
      "sahits": [],
      "muhurats": []
    },
    "eventDetails": [
      {
        "id": 5,
        "category": {
          "name": "Other",
          "id": 175581
        },
        "displayType": "Calendar Event",
        "title": {
          "np": "रोपाइँ जात्रा (दथुसायमतया)",
          "en": "Ropai Jatra"
        },
        "isHoliday": false,
        "location": null,
        "timing": {
          "from": null,
          "to": null
        },
        "details": {
          "en": null,
          "np": null
        }
      }
    ]
  },
  {
    "calendarInfo": {
      "dates": {
        "bs": {
          "year": {
            "np": "२०२७",
            "en": "2027"
          },
          "month": {
            "np": "भाद्र",
            "code": {
              "np": "५",
              "en": "5"
            },
            "en": "Bhadra"
          },
          "day": {
            "np": "३",
            "en": "3"
          },
          "full": {
            "np": "२०२७-५-३",
            "en": "2027-5-3"
          }
        },
        "ad": {
          "year": {
            "np": "१९७०",
            "en": "1970"
          },
          "month": {
            "np": null,
            "code": {
              "np": null,
              "en": "8"
            },
            "en": "August"
          },
          "day": {
            "np": "१९",
            "en": "19"
          },
          "full": {
            "np": "१९७०-०८-१९",
            "en": "1970-8-19"
          }
        }
      },
      "days": {
        "dayOfWeek": {
          "np": "बुधवार",
          "en": "Wednesday"
        },
        "codes": {
          "np": null,
          "en": "4"
        }
      },
      "nepaliEra": {
        "sakSambat": {
          "np": null,
          "en": null
        },
        "nepalSambat": {
          "year": {
            "np": "१०९०",
            "en": "1090"
          },
          "month": {
            "np": null,
            "code": {
              "np": null,
              "en": null
            },
            "en": null
          }
        }
      }
    },
    "tithiDetails": null,
    "panchangaDetails": null,
    "hrituDetails": null,
    "auspiciousMoments": {
      "sahits": [],
      "muhurats": []
    },
    "eventDetails": []
  },
  {
    "calendarInfo": {
      "dates": {
        "bs": {
          "year": {
            "np": "२०२७",
            "en": "2027"
          },
          "month": {
            "np": "भाद्र",
            "code": {
              "np": "५",
              "en": "5"
            },
            "en": "Bhadra"
          },
          "day": {
            "np": "४",
            "en": "4"
          },
          "full": {
            "np": "२०२७-५-४",
            "en": "2027-5-4"
          }
        },
        "ad": {
          "year": {
            "np": "१९७०",
            "en": "1970"
          },
          "month": {
            "np": null,
            "code": {
              "np": null,
              "en": "8"
            },
            "en": "August"
          },
          "day": {
            "np": "२०",
            "en": "20"
          },
          "full": {
            "np": "१९७०-०८-२०",
            "en": "1970-8-20"
          }
        }
      },
      "days": {
        "dayOfWeek": {
          "np": "बिहिवार",
          "en": "Thursday"
        },
        "codes": {
          "np": null,
          "en": "5"
        }
      },
      "nepaliEra": {
        "sakSambat": {
          "np": null,
          "en": null
        },
        "nepalSambat": {
          "year": {
            "np": "१०९०",
            "en": "1090"
          },
          "month": {
            "np": null,
            "code": {
              "np": null,
              "en": null
            },
            "en": null
          }
        }
      }
    },
    "tithiDetails": null,
    "panchangaDetails": null,
    "hrituDetails": null,
    "auspiciousMoments": {
      "sahits": [],
      "muhurats": []
    },
    "eventDetails": [
      {
        "id": 5,
        "category": {
          "name": "Other",
          "id": 124440
        },
        "displayType": "Calendar Event",
        "title": {
          "np": "राष्ट्रिय बाल दिवस",
          "en": "National Childrens Day"
        },
        "isHoliday": false,
        "location": null,
        "timing": {
          "from": null,
          "to": null
        },
        "details": {
          "en": null,
          "np": null
        }
      }
    ]
  },
  {
    "calendarInfo": {
      "dates": {
        "bs": {
          "year": {
            "np": "२०२७",
            "en": "2027"
          },
          "month": {
            "np": "भाद्र",
            "code": {
              "np": "५",
              "en": "5"
            },
            "en": "Bhadra"
          },
          "day": {
            "np": "५",
            "en": "5"
          },
          "full": {
            "np": "२०२७-५-५",
            "en": "2027-5-5"
          }
        },
        "ad": {
          "year": {
            "np": "१९७०",
            "en": "1970"
          },
          "month": {
            "np": null,
            "code": {
              "np": null,
              "en": "8"
            },
            "en": "August"
          },
          "day": {
            "np": "२१",
            "en": "21"
          },
          "full": {
            "np": "१९७०-०८-२१",
            "en": "1970-8-21"
          }
        }
      },
      "days": {
        "dayOfWeek": {
          "np": "शुक्रवार",
          "en": "Friday"
        },
        "codes": {
          "np": null,
          "en": "6"
        }
      },
      "nepaliEra": {
        "sakSambat": {
          "np": null,
          "en": null
        },
        "nepalSambat": {
          "year": {
            "np": "१०९०",
            "en": "1090"
          },
          "month": {
            "np": null,
            "code": {
              "np": null,
              "en": null
            },
            "en": null
          }
        }
      }
    },
    "tithiDetails": null,
    "panchangaDetails": null,
    "hrituDetails": null,
    "auspiciousMoments": {
      "sahits": [],
      "muhurats": []
    },
    "eventDetails": []
  },
  {
    "calendarInfo": {
      "dates": {
        "bs": {
          "year": {
            "np": "२०२७",
            "en": "2027"
          },
          "month": {
            "np": "भाद्र",
            "code": {
              "np": "५",
              "en": "5"
            },
            "en": "Bhadra"
          },
          "day": {
            "np": "६",
            "en": "6"
          },
          "full": {
            "np": "२०२७-५-६",
            "en": "2027-5-6"
          }
        },
        "ad": {
          "year": {
            "np": "१९७०",
            "en": "1970"
          },
          "month": {
            "np": null,
            "code": {
              "np": null,
              "en": "8"
            },
            "en": "August"
          },
          "day": {
            "np": "२२",
            "en": "22"
          },
          "full": {
            "np": "१९७०-०८-२२",
            "en": "1970-8-22"
          }
        }
      },
      "days": {
        "dayOfWeek": {
          "np": "शनिवार",
          "en": "Saturday"
        },
        "codes": {
          "np": null,
          "en": "7"
        }
      },
      "nepaliEra": {
        "sakSambat": {
          "np": null,
          "en": null
        },
        "nepalSambat": {
          "year": {
            "np": "१०९०",
            "en": "1090"
          },
          "month": {
            "np": null,
            "code": {
              "np": null,
              "en": null
            },
            "en": null
          }
        }
      }
    },
    "tithiDetails": null,
    "panchangaDetails": null,
    "hrituDetails": null,
    "auspiciousMoments": {
      "sahits": [],
      "muhurats": []
    },
    "eventDetails": [
      {
        "id": 5,
        "category": {
          "name": "Other",
          "id": 123980
        },
        "displayType": "Calendar Event",
        "title": {
          "np": "चन्द्र षष्ठी व्रत",
          "en": "Chandra Sasthi Brata"
        },
        "isHoliday": false,
        "location": null,
        "timing": {
          "from": null,
          "to": null
        },
        "details": {
          "en": null,
          "np": null
        }
      }
    ]
  },
  {
    "calendarInfo": {
      "dates": {
        "bs": {
          "year": {
            "np": "२०२७",
            "en": "2027"
          },
          "month": {
            "np": "भाद्र",
            "code": {
              "np": "५",
              "en": "5"
            },
            "en": "Bhadra"
          },
          "day": {
            "np": "७",
            "en": "7"
          },
          "full": {
            "np": "२०२७-५-७",
            "en": "2027-5-7"
          }
        },
        "ad": {
          "year": {
            "np": "१९७०",
            "en": "1970"
          },
          "month": {
            "np": null,
            "code": {
              "np": null,
              "en": "8"
            },
            "en": "August"
          },
          "day": {
            "np": "२३",
            "en": "23"
          },
          "full": {
            "np": "१९७०-०८-२३",
            "en": "1970-8-23"
          }
        }
      },
      "days": {
        "dayOfWeek": {
          "np": "आइतवार",
          "en": "Sunday"
        },
        "codes": {
          "np": null,
          "en": "1"
        }
      },
      "nepaliEra": {
        "sakSambat": {
          "np": null,
          "en": null
        },
        "nepalSambat": {
          "year": {
            "np": "१०९०",
            "en": "1090"
          },
          "month": {
            "np": null,
            "code": {
              "np": null,
              "en": null
            },
            "en": null
          }
        }
      }
    },
    "tithiDetails": null,
    "panchangaDetails": null,
    "hrituDetails": null,
    "auspiciousMoments": {
      "sahits": [],
      "muhurats": []
    },
    "eventDetails": [
      {
        "id": 5,
        "category": {
          "name": "others",
          "id": 230941
        },
        "displayType": "Calendar Event",
        "title": {
          "np": "रवि सप्तमी",
          "en": "Ravi Saptami Brat"
        },
        "isHoliday": false,
        "location": null,
        "timing": {
          "from": null,
          "to": null
        },
        "details": {
          "en": null,
          "np": null
        }
      }
    ]
  },
  {
    "calendarInfo": {
      "dates": {
        "bs": {
          "year": {
            "np": "२०२७",
            "en": "2027"
          },
          "month": {
            "np": "भाद्र",
            "code": {
              "np": "५",
              "en": "5"
            },
            "en": "Bhadra"
          },
          "day": {
            "np": "८",
            "en": "8"
          },
          "full": {
            "np": "२०२७-५-८",
            "en": "2027-5-8"
          }
        },
        "ad": {
          "year": {
            "np": "१९७०",
            "en": "1970"
          },
          "month": {
            "np": null,
            "code": {
              "np": null,
              "en": "8"
            },
            "en": "August"
          },
          "day": {
            "np": "२४",
            "en": "24"
          },
          "full": {
            "np": "१९७०-०८-२४",
            "en": "1970-8-24"
          }
        }
      },
      "days": {
        "dayOfWeek": {
          "np": "सोमवार",
          "en": "Monday"
        },
        "codes": {
          "np": null,
          "en": "2"
        }
      },
      "nepaliEra": {
        "sakSambat": {
          "np": null,
          "en": null
        },
        "nepalSambat": {
          "year": {
            "np": "१०९०",
            "en": "1090"
          },
          "month": {
            "np": null,
            "code": {
              "np": null,
              "en": null
            },
            "en": null
          }
        }
      }
    },
    "tithiDetails": null,
    "panchangaDetails": null,
    "hrituDetails": null,
    "auspiciousMoments": {
      "sahits": [],
      "muhurats": []
    },
    "eventDetails": [
      {
        "id": 5,
        "category": {
          "name": "Other",
          "id": 123997
        },
        "displayType": "Calendar Event",
        "title": {
          "np": "मोह रात्री",
          "en": "Moha Ratri"
        },
        "isHoliday": false,
        "location": null,
        "timing": {
          "from": null,
          "to": null
        },
        "details": {
          "en": null,
          "np": null
        }
      },
      {
        "id": 5,
        "category": {
          "name": "Other",
          "id": 124263
        },
        "displayType": "Calendar Event",
        "title": {
          "np": "दुर्वा अष्टमी व्रत",
          "en": "Durwa Astami"
        },
        "isHoliday": false,
        "location": null,
        "timing": {
          "from": null,
          "to": null
        },
        "details": {
          "en": null,
          "np": null
        }
      },
      {
        "id": 5,
        "category": {
          "name": "Other",
          "id": 124414
        },
        "displayType": "Calendar Event",
        "title": {
          "np": "श्रिकृष्ण जन्माष्टमी व्रत",
          "en": "Shree Krishna Janmasthami Brata (Moharatri)"
        },
        "isHoliday": false,
        "location": null,
        "timing": {
          "from": null,
          "to": null
        },
        "details": {
          "en": null,
          "np": null
        }
      }
    ]
  },
  {
    "calendarInfo": {
      "dates": {
        "bs": {
          "year": {
            "np": "२०२७",
            "en": "2027"
          },
          "month": {
            "np": "भाद्र",
            "code": {
              "np": "५",
              "en": "5"
            },
            "en": "Bhadra"
          },
          "day": {
            "np": "९",
            "en": "9"
          },
          "full": {
            "np": "२०२७-५-९",
            "en": "2027-5-9"
          }
        },
        "ad": {
          "year": {
            "np": "१९७०",
            "en": "1970"
          },
          "month": {
            "np": null,
            "code": {
              "np": null,
              "en": "8"
            },
            "en": "August"
          },
          "day": {
            "np": "२५",
            "en": "25"
          },
          "full": {
            "np": "१९७०-०८-२५",
            "en": "1970-8-25"
          }
        }
      },
      "days": {
        "dayOfWeek": {
          "np": "मङ्गलवार",
          "en": "Tuesday"
        },
        "codes": {
          "np": null,
          "en": "3"
        }
      },
      "nepaliEra": {
        "sakSambat": {
          "np": null,
          "en": null
        },
        "nepalSambat": {
          "year": {
            "np": "१०९०",
            "en": "1090"
          },
          "month": {
            "np": null,
            "code": {
              "np": null,
              "en": null
            },
            "en": null
          }
        }
      }
    },
    "tithiDetails": null,
    "panchangaDetails": null,
    "hrituDetails": null,
    "auspiciousMoments": {
      "sahits": [],
      "muhurats": []
    },
    "eventDetails": [
      {
        "id": 5,
        "category": {
          "name": "Other",
          "id": 124054
        },
        "displayType": "Calendar Event",
        "title": {
          "np": "गुगा नवमी",
          "en": "Guga Nawami"
        },
        "isHoliday": false,
        "location": null,
        "timing": {
          "from": null,
          "to": null
        },
        "details": {
          "en": null,
          "np": null
        }
      }
    ]
  },
  {
    "calendarInfo": {
      "dates": {
        "bs": {
          "year": {
            "np": "२०२७",
            "en": "2027"
          },
          "month": {
            "np": "भाद्र",
            "code": {
              "np": "५",
              "en": "5"
            },
            "en": "Bhadra"
          },
          "day": {
            "np": "१०",
            "en": "10"
          },
          "full": {
            "np": "२०२७-५-१०",
            "en": "2027-5-10"
          }
        },
        "ad": {
          "year": {
            "np": "१९७०",
            "en": "1970"
          },
          "month": {
            "np": null,
            "code": {
              "np": null,
              "en": "8"
            },
            "en": "August"
          },
          "day": {
            "np": "२६",
            "en": "26"
          },
          "full": {
            "np": "१९७०-०८-२६",
            "en": "1970-8-26"
          }
        }
      },
      "days": {
        "dayOfWeek": {
          "np": "बुधवार",
          "en": "Wednesday"
        },
        "codes": {
          "np": null,
          "en": "4"
        }
      },
      "nepaliEra": {
        "sakSambat": {
          "np": null,
          "en": null
        },
        "nepalSambat": {
          "year": {
            "np": "१०९०",
            "en": "1090"
          },
          "month": {
            "np": null,
            "code": {
              "np": null,
              "en": null
            },
            "en": null
          }
        }
      }
    },
    "tithiDetails": null,
    "panchangaDetails": null,
    "hrituDetails": null,
    "auspiciousMoments": {
      "sahits": [],
      "muhurats": []
    },
    "eventDetails": []
  },
  {
    "calendarInfo": {
      "dates": {
        "bs": {
          "year": {
            "np": "२०२७",
            "en": "2027"
          },
          "month": {
            "np": "भाद्र",
            "code": {
              "np": "५",
              "en": "5"
            },
            "en": "Bhadra"
          },
          "day": {
            "np": "११",
            "en": "11"
          },
          "full": {
            "np": "२०२७-५-११",
            "en": "2027-5-11"
          }
        },
        "ad": {
          "year": {
            "np": "१९७०",
            "en": "1970"
          },
          "month": {
            "np": null,
            "code": {
              "np": null,
              "en": "8"
            },
            "en": "August"
          },
          "day": {
            "np": "२७",
            "en": "27"
          },
          "full": {
            "np": "१९७०-०८-२७",
            "en": "1970-8-27"
          }
        }
      },
      "days": {
        "dayOfWeek": {
          "np": "बिहिवार",
          "en": "Thursday"
        },
        "codes": {
          "np": null,
          "en": "5"
        }
      },
      "nepaliEra": {
        "sakSambat": {
          "np": null,
          "en": null
        },
        "nepalSambat": {
          "year": {
            "np": "१०९०",
            "en": "1090"
          },
          "month": {
            "np": null,
            "code": {
              "np": null,
              "en": null
            },
            "en": null
          }
        }
      }
    },
    "tithiDetails": null,
    "panchangaDetails": null,
    "hrituDetails": null,
    "auspiciousMoments": {
      "sahits": [],
      "muhurats": []
    },
    "eventDetails": [
      {
        "id": 5,
        "category": {
          "name": "Other",
          "id": 124413
        },
        "displayType": "Calendar Event",
        "title": {
          "np": "अजा एकादशी व्रत",
          "en": "Samartako Aja Ekadasi Brata"
        },
        "isHoliday": false,
        "location": null,
        "timing": {
          "from": null,
          "to": null
        },
        "details": {
          "en": null,
          "np": null
        }
      }
    ]
  },
  {
    "calendarInfo": {
      "dates": {
        "bs": {
          "year": {
            "np": "२०२७",
            "en": "2027"
          },
          "month": {
            "np": "भाद्र",
            "code": {
              "np": "५",
              "en": "5"
            },
            "en": "Bhadra"
          },
          "day": {
            "np": "१२",
            "en": "12"
          },
          "full": {
            "np": "२०२७-५-१२",
            "en": "2027-5-12"
          }
        },
        "ad": {
          "year": {
            "np": "१९७०",
            "en": "1970"
          },
          "month": {
            "np": null,
            "code": {
              "np": null,
              "en": "8"
            },
            "en": "August"
          },
          "day": {
            "np": "२८",
            "en": "28"
          },
          "full": {
            "np": "१९७०-०८-२८",
            "en": "1970-8-28"
          }
        }
      },
      "days": {
        "dayOfWeek": {
          "np": "शुक्रवार",
          "en": "Friday"
        },
        "codes": {
          "np": null,
          "en": "6"
        }
      },
      "nepaliEra": {
        "sakSambat": {
          "np": null,
          "en": null
        },
        "nepalSambat": {
          "year": {
            "np": "१०९०",
            "en": "1090"
          },
          "month": {
            "np": null,
            "code": {
              "np": null,
              "en": null
            },
            "en": null
          }
        }
      }
    },
    "tithiDetails": null,
    "panchangaDetails": null,
    "hrituDetails": null,
    "auspiciousMoments": {
      "sahits": [],
      "muhurats": []
    },
    "eventDetails": []
  },
  {
    "calendarInfo": {
      "dates": {
        "bs": {
          "year": {
            "np": "२०२७",
            "en": "2027"
          },
          "month": {
            "np": "भाद्र",
            "code": {
              "np": "५",
              "en": "5"
            },
            "en": "Bhadra"
          },
          "day": {
            "np": "१३",
            "en": "13"
          },
          "full": {
            "np": "२०२७-५-१३",
            "en": "2027-5-13"
          }
        },
        "ad": {
          "year": {
            "np": "१९७०",
            "en": "1970"
          },
          "month": {
            "np": null,
            "code": {
              "np": null,
              "en": "8"
            },
            "en": "August"
          },
          "day": {
            "np": "२९",
            "en": "29"
          },
          "full": {
            "np": "१९७०-०८-२९",
            "en": "1970-8-29"
          }
        }
      },
      "days": {
        "dayOfWeek": {
          "np": "शनिवार",
          "en": "Saturday"
        },
        "codes": {
          "np": null,
          "en": "7"
        }
      },
      "nepaliEra": {
        "sakSambat": {
          "np": null,
          "en": null
        },
        "nepalSambat": {
          "year": {
            "np": "१०९०",
            "en": "1090"
          },
          "month": {
            "np": null,
            "code": {
              "np": null,
              "en": null
            },
            "en": null
          }
        }
      }
    },
    "tithiDetails": null,
    "panchangaDetails": null,
    "hrituDetails": null,
    "auspiciousMoments": {
      "sahits": [],
      "muhurats": []
    },
    "eventDetails": []
  },
  {
    "calendarInfo": {
      "dates": {
        "bs": {
          "year": {
            "np": "२०२७",
            "en": "2027"
          },
          "month": {
            "np": "भाद्र",
            "code": {
              "np": "५",
              "en": "5"
            },
            "en": "Bhadra"
          },
          "day": {
            "np": "१४",
            "en": "14"
          },
          "full": {
            "np": "२०२७-५-१४",
            "en": "2027-5-14"
          }
        },
        "ad": {
          "year": {
            "np": "१९७०",
            "en": "1970"
          },
          "month": {
            "np": null,
            "code": {
              "np": null,
              "en": "8"
            },
            "en": "August"
          },
          "day": {
            "np": "३०",
            "en": "30"
          },
          "full": {
            "np": "१९७०-०८-३०",
            "en": "1970-8-30"
          }
        }
      },
      "days": {
        "dayOfWeek": {
          "np": "आइतवार",
          "en": "Sunday"
        },
        "codes": {
          "np": null,
          "en": "1"
        }
      },
      "nepaliEra": {
        "sakSambat": {
          "np": null,
          "en": null
        },
        "nepalSambat": {
          "year": {
            "np": "१०९०",
            "en": "1090"
          },
          "month": {
            "np": null,
            "code": {
              "np": null,
              "en": null
            },
            "en": null
          }
        }
      }
    },
    "tithiDetails": null,
    "panchangaDetails": null,
    "hrituDetails": null,
    "auspiciousMoments": {
      "sahits": [],
      "muhurats": []
    },
    "eventDetails": [
      {
        "id": 5,
        "category": {
          "name": "Other",
          "id": 124045
        },
        "displayType": "Calendar Event",
        "title": {
          "np": "जुगा चर्हे पूजा",
          "en": "Juga Chhare Puja"
        },
        "isHoliday": false,
        "location": null,
        "timing": {
          "from": null,
          "to": null
        },
        "details": {
          "en": null,
          "np": null
        }
      }
    ]
  },
  {
    "calendarInfo": {
      "dates": {
        "bs": {
          "year": {
            "np": "२०२७",
            "en": "2027"
          },
          "month": {
            "np": "भाद्र",
            "code": {
              "np": "५",
              "en": "5"
            },
            "en": "Bhadra"
          },
          "day": {
            "np": "१५",
            "en": "15"
          },
          "full": {
            "np": "२०२७-५-१५",
            "en": "2027-5-15"
          }
        },
        "ad": {
          "year": {
            "np": "१९७०",
            "en": "1970"
          },
          "month": {
            "np": null,
            "code": {
              "np": null,
              "en": "8"
            },
            "en": "August"
          },
          "day": {
            "np": "३१",
            "en": "31"
          },
          "full": {
            "np": "१९७०-०८-३१",
            "en": "1970-8-31"
          }
        }
      },
      "days": {
        "dayOfWeek": {
          "np": "सोमवार",
          "en": "Monday"
        },
        "codes": {
          "np": null,
          "en": "2"
        }
      },
      "nepaliEra": {
        "sakSambat": {
          "np": null,
          "en": null
        },
        "nepalSambat": {
          "year": {
            "np": "१०९०",
            "en": "1090"
          },
          "month": {
            "np": null,
            "code": {
              "np": null,
              "en": null
            },
            "en": null
          }
        }
      }
    },
    "tithiDetails": null,
    "panchangaDetails": null,
    "hrituDetails": null,
    "auspiciousMoments": {
      "sahits": [],
      "muhurats": []
    },
    "eventDetails": [
      {
        "id": 5,
        "category": {
          "name": "Other",
          "id": 124066
        },
        "displayType": "Calendar Event",
        "title": {
          "np": "बुबाको मुख हेर्ने दिवस",
          "en": "Kushe Aushi / Father's Day"
        },
        "isHoliday": false,
        "location": null,
        "timing": {
          "from": null,
          "to": null
        },
        "details": {
          "en": null,
          "np": null
        }
      },
      {
        "id": 5,
        "category": {
          "name": "Other",
          "id": 124409
        },
        "displayType": "Calendar Event",
        "title": {
          "np": "हलो बार्ने",
          "en": "Halo Barne"
        },
        "isHoliday": false,
        "location": null,
        "timing": {
          "from": null,
          "to": null
        },
        "details": {
          "en": null,
          "np": null
        }
      },
      {
        "id": 5,
        "category": {
          "name": "Other",
          "id": 124410
        },
        "displayType": "Calendar Event",
        "title": {
          "np": "निशि बार्ने",
          "en": "Nishi Barne "
        },
        "isHoliday": false,
        "location": null,
        "timing": {
          "from": null,
          "to": null
        },
        "details": {
          "en": null,
          "np": null
        }
      },
      {
        "id": 5,
        "category": {
          "name": "Other",
          "id": 124411
        },
        "displayType": "Calendar Event",
        "title": {
          "np": "मोतिराम जयन्ती",
          "en": "Motiram Jayanti"
        },
        "isHoliday": false,
        "location": null,
        "timing": {
          "from": null,
          "to": null
        },
        "details": {
          "en": null,
          "np": null
        }
      },
      {
        "id": 5,
        "category": {
          "name": "Other",
          "id": 124412
        },
        "displayType": "Calendar Event",
        "title": {
          "np": "कुशे औँशी",
          "en": "Kushe Aushi"
        },
        "isHoliday": false,
        "location": null,
        "timing": {
          "from": null,
          "to": null
        },
        "details": {
          "en": null,
          "np": null
        }
      },
      {
        "id": 5,
        "category": {
          "name": "others",
          "id": 230929
        },
        "displayType": "Calendar Event",
        "title": {
          "np": "सोमबारे औंसी",
          "en": "Sombare Ausi"
        },
        "isHoliday": false,
        "location": null,
        "timing": {
          "from": null,
          "to": null
        },
        "details": {
          "en": null,
          "np": null
        }
      }
    ]
  },
  {
    "calendarInfo": {
      "dates": {
        "bs": {
          "year": {
            "np": "२०२७",
            "en": "2027"
          },
          "month": {
            "np": "भाद्र",
            "code": {
              "np": "५",
              "en": "5"
            },
            "en": "Bhadra"
          },
          "day": {
            "np": "१६",
            "en": "16"
          },
          "full": {
            "np": "२०२७-५-१६",
            "en": "2027-5-16"
          }
        },
        "ad": {
          "year": {
            "np": "१९७०",
            "en": "1970"
          },
          "month": {
            "np": null,
            "code": {
              "np": null,
              "en": "9"
            },
            "en": "September"
          },
          "day": {
            "np": "०१",
            "en": "1"
          },
          "full": {
            "np": "१९७०-०९-०१",
            "en": "1970-9-1"
          }
        }
      },
      "days": {
        "dayOfWeek": {
          "np": "मङ्गलवार",
          "en": "Tuesday"
        },
        "codes": {
          "np": null,
          "en": "3"
        }
      },
      "nepaliEra": {
        "sakSambat": {
          "np": null,
          "en": null
        },
        "nepalSambat": {
          "year": {
            "np": "१०९०",
            "en": "1090"
          },
          "month": {
            "np": null,
            "code": {
              "np": null,
              "en": null
            },
            "en": null
          }
        }
      }
    },
    "tithiDetails": null,
    "panchangaDetails": null,
    "hrituDetails": null,
    "auspiciousMoments": {
      "sahits": [],
      "muhurats": []
    },
    "eventDetails": [
      {
        "id": 5,
        "category": {
          "name": "Other",
          "id": 124408
        },
        "displayType": "Calendar Event",
        "title": {
          "np": "गुँला पर्व समाप्ती",
          "en": "Gunlla Parwa Ends"
        },
        "isHoliday": false,
        "location": null,
        "timing": {
          "from": null,
          "to": null
        },
        "details": {
          "en": null,
          "np": null
        }
      }
    ]
  },
  {
    "calendarInfo": {
      "dates": {
        "bs": {
          "year": {
            "np": "२०२७",
            "en": "2027"
          },
          "month": {
            "np": "भाद्र",
            "code": {
              "np": "५",
              "en": "5"
            },
            "en": "Bhadra"
          },
          "day": {
            "np": "१७",
            "en": "17"
          },
          "full": {
            "np": "२०२७-५-१७",
            "en": "2027-5-17"
          }
        },
        "ad": {
          "year": {
            "np": "१९७०",
            "en": "1970"
          },
          "month": {
            "np": null,
            "code": {
              "np": null,
              "en": "9"
            },
            "en": "September"
          },
          "day": {
            "np": "०२",
            "en": "2"
          },
          "full": {
            "np": "१९७०-०९-०२",
            "en": "1970-9-2"
          }
        }
      },
      "days": {
        "dayOfWeek": {
          "np": "बुधवार",
          "en": "Wednesday"
        },
        "codes": {
          "np": null,
          "en": "4"
        }
      },
      "nepaliEra": {
        "sakSambat": {
          "np": null,
          "en": null
        },
        "nepalSambat": {
          "year": {
            "np": "१०९०",
            "en": "1090"
          },
          "month": {
            "np": null,
            "code": {
              "np": null,
              "en": null
            },
            "en": null
          }
        }
      }
    },
    "tithiDetails": null,
    "panchangaDetails": null,
    "hrituDetails": null,
    "auspiciousMoments": {
      "sahits": [],
      "muhurats": []
    },
    "eventDetails": [
      {
        "id": 5,
        "category": {
          "name": "Other",
          "id": 124407
        },
        "displayType": "Calendar Event",
        "title": {
          "np": "दर खाने दिन",
          "en": "Teejako Dar Khaane"
        },
        "isHoliday": false,
        "location": null,
        "timing": {
          "from": null,
          "to": null
        },
        "details": {
          "en": null,
          "np": null
        }
      }
    ]
  },
  {
    "calendarInfo": {
      "dates": {
        "bs": {
          "year": {
            "np": "२०२७",
            "en": "2027"
          },
          "month": {
            "np": "भाद्र",
            "code": {
              "np": "५",
              "en": "5"
            },
            "en": "Bhadra"
          },
          "day": {
            "np": "१८",
            "en": "18"
          },
          "full": {
            "np": "२०२७-५-१८",
            "en": "2027-5-18"
          }
        },
        "ad": {
          "year": {
            "np": "१९७०",
            "en": "1970"
          },
          "month": {
            "np": null,
            "code": {
              "np": null,
              "en": "9"
            },
            "en": "September"
          },
          "day": {
            "np": "०३",
            "en": "3"
          },
          "full": {
            "np": "१९७०-०९-०३",
            "en": "1970-9-3"
          }
        }
      },
      "days": {
        "dayOfWeek": {
          "np": "बिहिवार",
          "en": "Thursday"
        },
        "codes": {
          "np": null,
          "en": "5"
        }
      },
      "nepaliEra": {
        "sakSambat": {
          "np": null,
          "en": null
        },
        "nepalSambat": {
          "year": {
            "np": "१०९०",
            "en": "1090"
          },
          "month": {
            "np": null,
            "code": {
              "np": null,
              "en": null
            },
            "en": null
          }
        }
      }
    },
    "tithiDetails": null,
    "panchangaDetails": null,
    "hrituDetails": null,
    "auspiciousMoments": {
      "sahits": [],
      "muhurats": []
    },
    "eventDetails": []
  },
  {
    "calendarInfo": {
      "dates": {
        "bs": {
          "year": {
            "np": "२०२७",
            "en": "2027"
          },
          "month": {
            "np": "भाद्र",
            "code": {
              "np": "५",
              "en": "5"
            },
            "en": "Bhadra"
          },
          "day": {
            "np": "१९",
            "en": "19"
          },
          "full": {
            "np": "२०२७-५-१९",
            "en": "2027-5-19"
          }
        },
        "ad": {
          "year": {
            "np": "१९७०",
            "en": "1970"
          },
          "month": {
            "np": null,
            "code": {
              "np": null,
              "en": "9"
            },
            "en": "September"
          },
          "day": {
            "np": "०४",
            "en": "4"
          },
          "full": {
            "np": "१९७०-०९-०४",
            "en": "1970-9-4"
          }
        }
      },
      "days": {
        "dayOfWeek": {
          "np": "शुक्रवार",
          "en": "Friday"
        },
        "codes": {
          "np": null,
          "en": "6"
        }
      },
      "nepaliEra": {
        "sakSambat": {
          "np": null,
          "en": null
        },
        "nepalSambat": {
          "year": {
            "np": "१०९०",
            "en": "1090"
          },
          "month": {
            "np": null,
            "code": {
              "np": null,
              "en": null
            },
            "en": null
          }
        }
      }
    },
    "tithiDetails": null,
    "panchangaDetails": null,
    "hrituDetails": null,
    "auspiciousMoments": {
      "sahits": [],
      "muhurats": []
    },
    "eventDetails": [
      {
        "id": 5,
        "category": {
          "name": "Other",
          "id": 124102
        },
        "displayType": "Calendar Event",
        "title": {
          "np": "बराह जयन्ति",
          "en": "Baraha Jayanti"
        },
        "isHoliday": false,
        "location": null,
        "timing": {
          "from": null,
          "to": null
        },
        "details": {
          "en": null,
          "np": null
        }
      },
      {
        "id": 5,
        "category": {
          "name": "Other",
          "id": 124406
        },
        "displayType": "Calendar Event",
        "title": {
          "np": "हरितालिका तिज व्रत (महिला मात्र)",
          "en": "Haritalika Teej Brata (Women only)"
        },
        "isHoliday": false,
        "location": null,
        "timing": {
          "from": null,
          "to": null
        },
        "details": {
          "en": null,
          "np": null
        }
      }
    ]
  },
  {
    "calendarInfo": {
      "dates": {
        "bs": {
          "year": {
            "np": "२०२७",
            "en": "2027"
          },
          "month": {
            "np": "भाद्र",
            "code": {
              "np": "५",
              "en": "5"
            },
            "en": "Bhadra"
          },
          "day": {
            "np": "२०",
            "en": "20"
          },
          "full": {
            "np": "२०२७-५-२०",
            "en": "2027-5-20"
          }
        },
        "ad": {
          "year": {
            "np": "१९७०",
            "en": "1970"
          },
          "month": {
            "np": null,
            "code": {
              "np": null,
              "en": "9"
            },
            "en": "September"
          },
          "day": {
            "np": "०५",
            "en": "5"
          },
          "full": {
            "np": "१९७०-०९-०५",
            "en": "1970-9-5"
          }
        }
      },
      "days": {
        "dayOfWeek": {
          "np": "शनिवार",
          "en": "Saturday"
        },
        "codes": {
          "np": null,
          "en": "7"
        }
      },
      "nepaliEra": {
        "sakSambat": {
          "np": null,
          "en": null
        },
        "nepalSambat": {
          "year": {
            "np": "१०९०",
            "en": "1090"
          },
          "month": {
            "np": null,
            "code": {
              "np": null,
              "en": null
            },
            "en": null
          }
        }
      }
    },
    "tithiDetails": null,
    "panchangaDetails": null,
    "hrituDetails": null,
    "auspiciousMoments": {
      "sahits": [],
      "muhurats": []
    },
    "eventDetails": [
      {
        "id": 5,
        "category": {
          "name": "Other",
          "id": 124099
        },
        "displayType": "Calendar Event",
        "title": {
          "np": "चन्द्रदर्शन दोष",
          "en": "Chandradarsan, Dosh:Chatha"
        },
        "isHoliday": false,
        "location": null,
        "timing": {
          "from": null,
          "to": null
        },
        "details": {
          "en": null,
          "np": null
        }
      },
      {
        "id": 5,
        "category": {
          "name": "Other",
          "id": 124405
        },
        "displayType": "Calendar Event",
        "title": {
          "np": "गणेश चतुर्थी व्रत",
          "en": "Ganesh Chaturthi"
        },
        "isHoliday": false,
        "location": null,
        "timing": {
          "from": null,
          "to": null
        },
        "details": {
          "en": null,
          "np": null
        }
      }
    ]
  },
  {
    "calendarInfo": {
      "dates": {
        "bs": {
          "year": {
            "np": "२०२७",
            "en": "2027"
          },
          "month": {
            "np": "भाद्र",
            "code": {
              "np": "५",
              "en": "5"
            },
            "en": "Bhadra"
          },
          "day": {
            "np": "२१",
            "en": "21"
          },
          "full": {
            "np": "२०२७-५-२१",
            "en": "2027-5-21"
          }
        },
        "ad": {
          "year": {
            "np": "१९७०",
            "en": "1970"
          },
          "month": {
            "np": null,
            "code": {
              "np": null,
              "en": "9"
            },
            "en": "September"
          },
          "day": {
            "np": "०६",
            "en": "6"
          },
          "full": {
            "np": "१९७०-०९-०६",
            "en": "1970-9-6"
          }
        }
      },
      "days": {
        "dayOfWeek": {
          "np": "आइतवार",
          "en": "Sunday"
        },
        "codes": {
          "np": null,
          "en": "1"
        }
      },
      "nepaliEra": {
        "sakSambat": {
          "np": null,
          "en": null
        },
        "nepalSambat": {
          "year": {
            "np": "१०९०",
            "en": "1090"
          },
          "month": {
            "np": null,
            "code": {
              "np": null,
              "en": null
            },
            "en": null
          }
        }
      }
    },
    "tithiDetails": null,
    "panchangaDetails": null,
    "hrituDetails": null,
    "auspiciousMoments": {
      "sahits": [],
      "muhurats": []
    },
    "eventDetails": [
      {
        "id": 5,
        "category": {
          "name": "Other",
          "id": 124013
        },
        "displayType": "Calendar Event",
        "title": {
          "np": "कोखाजविय",
          "en": "Kokhaja Biye"
        },
        "isHoliday": false,
        "location": null,
        "timing": {
          "from": null,
          "to": null
        },
        "details": {
          "en": null,
          "np": null
        }
      },
      {
        "id": 5,
        "category": {
          "name": "Other",
          "id": 124403
        },
        "displayType": "Calendar Event",
        "title": {
          "np": "ऋिषी पन्चमी (महिला मात्र)",
          "en": "Rishi Panchami (Saptarishi Puja)"
        },
        "isHoliday": false,
        "location": null,
        "timing": {
          "from": null,
          "to": null
        },
        "details": {
          "en": null,
          "np": null
        }
      },
      {
        "id": 5,
        "category": {
          "name": "Other",
          "id": 124404
        },
        "displayType": "Calendar Event",
        "title": {
          "np": "सप्त ऋषी पूजा",
          "en": "Sapta Rishi Puja"
        },
        "isHoliday": false,
        "location": null,
        "timing": {
          "from": null,
          "to": null
        },
        "details": {
          "en": null,
          "np": null
        }
      },
      {
        "id": 620,
        "category": {
          "name": "others",
          "id": 493478
        },
        "displayType": "Calendar Event",
        "title": {
          "np": "विरूडा पञ्चमी",
          "en": "Biruda Panchami"
        },
        "isHoliday": false,
        "location": null,
        "timing": {
          "from": null,
          "to": null
        },
        "details": {
          "en": null,
          "np": null
        }
      }
    ]
  },
  {
    "calendarInfo": {
      "dates": {
        "bs": {
          "year": {
            "np": "२०२७",
            "en": "2027"
          },
          "month": {
            "np": "भाद्र",
            "code": {
              "np": "५",
              "en": "5"
            },
            "en": "Bhadra"
          },
          "day": {
            "np": "२२",
            "en": "22"
          },
          "full": {
            "np": "२०२७-५-२२",
            "en": "2027-5-22"
          }
        },
        "ad": {
          "year": {
            "np": "१९७०",
            "en": "1970"
          },
          "month": {
            "np": null,
            "code": {
              "np": null,
              "en": "9"
            },
            "en": "September"
          },
          "day": {
            "np": "०७",
            "en": "7"
          },
          "full": {
            "np": "१९७०-०९-०७",
            "en": "1970-9-7"
          }
        }
      },
      "days": {
        "dayOfWeek": {
          "np": "सोमवार",
          "en": "Monday"
        },
        "codes": {
          "np": null,
          "en": "2"
        }
      },
      "nepaliEra": {
        "sakSambat": {
          "np": null,
          "en": null
        },
        "nepalSambat": {
          "year": {
            "np": "१०९०",
            "en": "1090"
          },
          "month": {
            "np": null,
            "code": {
              "np": null,
              "en": null
            },
            "en": null
          }
        }
      }
    },
    "tithiDetails": null,
    "panchangaDetails": null,
    "hrituDetails": null,
    "auspiciousMoments": {
      "sahits": [],
      "muhurats": []
    },
    "eventDetails": [
      {
        "id": 5,
        "category": {
          "name": "Other",
          "id": 124100
        },
        "displayType": "Calendar Event",
        "title": {
          "np": "सूर्य षष्ठी व्रत",
          "en": "Surya Sasthi"
        },
        "isHoliday": false,
        "location": null,
        "timing": {
          "from": null,
          "to": null
        },
        "details": {
          "en": null,
          "np": null
        }
      }
    ]
  },
  {
    "calendarInfo": {
      "dates": {
        "bs": {
          "year": {
            "np": "२०२७",
            "en": "2027"
          },
          "month": {
            "np": "भाद्र",
            "code": {
              "np": "५",
              "en": "5"
            },
            "en": "Bhadra"
          },
          "day": {
            "np": "२३",
            "en": "23"
          },
          "full": {
            "np": "२०२७-५-२३",
            "en": "2027-5-23"
          }
        },
        "ad": {
          "year": {
            "np": "१९७०",
            "en": "1970"
          },
          "month": {
            "np": null,
            "code": {
              "np": null,
              "en": "9"
            },
            "en": "September"
          },
          "day": {
            "np": "०८",
            "en": "8"
          },
          "full": {
            "np": "१९७०-०९-०८",
            "en": "1970-9-8"
          }
        }
      },
      "days": {
        "dayOfWeek": {
          "np": "मङ्गलवार",
          "en": "Tuesday"
        },
        "codes": {
          "np": null,
          "en": "3"
        }
      },
      "nepaliEra": {
        "sakSambat": {
          "np": null,
          "en": null
        },
        "nepalSambat": {
          "year": {
            "np": "१०९०",
            "en": "1090"
          },
          "month": {
            "np": null,
            "code": {
              "np": null,
              "en": null
            },
            "en": null
          }
        }
      }
    },
    "tithiDetails": null,
    "panchangaDetails": null,
    "hrituDetails": null,
    "auspiciousMoments": {
      "sahits": [],
      "muhurats": []
    },
    "eventDetails": [
      {
        "id": 5,
        "category": {
          "name": "Other",
          "id": 124133
        },
        "displayType": "Calendar Event",
        "title": {
          "np": "विश्व शिक्षा तथा साक्षरता दिवस",
          "en": "World Literacy Day"
        },
        "isHoliday": false,
        "location": null,
        "timing": {
          "from": null,
          "to": null
        },
        "details": {
          "en": null,
          "np": null
        }
      },
      {
        "id": 5,
        "category": {
          "name": "Other",
          "id": 493483
        },
        "displayType": "Calendar Event",
        "title": {
          "np": "गौर सप्तमी व्रत",
          "en": "Gaura Saptami Brata"
        },
        "isHoliday": false,
        "location": null,
        "timing": {
          "from": null,
          "to": null
        },
        "details": {
          "en": null,
          "np": null
        }
      },
      {
        "id": 5,
        "category": {
          "name": "Other",
          "id": 493484
        },
        "displayType": "Calendar Event",
        "title": {
          "np": "अमुक्त भरण सप्तमी",
          "en": "Amukta Bharan Saptami"
        },
        "isHoliday": false,
        "location": null,
        "timing": {
          "from": null,
          "to": null
        },
        "details": {
          "en": null,
          "np": null
        }
      }
    ]
  },
  {
    "calendarInfo": {
      "dates": {
        "bs": {
          "year": {
            "np": "२०२७",
            "en": "2027"
          },
          "month": {
            "np": "भाद्र",
            "code": {
              "np": "५",
              "en": "5"
            },
            "en": "Bhadra"
          },
          "day": {
            "np": "२४",
            "en": "24"
          },
          "full": {
            "np": "२०२७-५-२४",
            "en": "2027-5-24"
          }
        },
        "ad": {
          "year": {
            "np": "१९७०",
            "en": "1970"
          },
          "month": {
            "np": null,
            "code": {
              "np": null,
              "en": "9"
            },
            "en": "September"
          },
          "day": {
            "np": "०९",
            "en": "9"
          },
          "full": {
            "np": "१९७०-०९-०९",
            "en": "1970-9-9"
          }
        }
      },
      "days": {
        "dayOfWeek": {
          "np": "बुधवार",
          "en": "Wednesday"
        },
        "codes": {
          "np": null,
          "en": "4"
        }
      },
      "nepaliEra": {
        "sakSambat": {
          "np": null,
          "en": null
        },
        "nepalSambat": {
          "year": {
            "np": "१०९०",
            "en": "1090"
          },
          "month": {
            "np": null,
            "code": {
              "np": null,
              "en": null
            },
            "en": null
          }
        }
      }
    },
    "tithiDetails": null,
    "panchangaDetails": null,
    "hrituDetails": null,
    "auspiciousMoments": {
      "sahits": [],
      "muhurats": []
    },
    "eventDetails": [
      {
        "id": 5,
        "category": {
          "name": "Other",
          "id": 124063
        },
        "displayType": "Calendar Event",
        "title": {
          "np": "गौरापर्व",
          "en": "Gaura Parwa (Related Field only)"
        },
        "isHoliday": false,
        "location": null,
        "timing": {
          "from": null,
          "to": null
        },
        "details": {
          "en": null,
          "np": null
        }
      },
      {
        "id": 5,
        "category": {
          "name": "Other",
          "id": 124401
        },
        "displayType": "Calendar Event",
        "title": {
          "np": "काया अष्टमी",
          "en": "Kaya:Astami"
        },
        "isHoliday": false,
        "location": null,
        "timing": {
          "from": null,
          "to": null
        },
        "details": {
          "en": null,
          "np": null
        }
      },
      {
        "id": 5,
        "category": {
          "name": "Other",
          "id": 124402
        },
        "displayType": "Calendar Event",
        "title": {
          "np": "महालक्ष्मि व्रतारम्भ",
          "en": "Mahalaxmi Brat Starts"
        },
        "isHoliday": false,
        "location": null,
        "timing": {
          "from": null,
          "to": null
        },
        "details": {
          "en": null,
          "np": null
        }
      },
      {
        "id": 5,
        "category": {
          "name": "others",
          "id": 230946
        },
        "displayType": "Calendar Event",
        "title": {
          "np": "बुधाष्टमी व्रत",
          "en": "Budhashtami Barta"
        },
        "isHoliday": false,
        "location": null,
        "timing": {
          "from": null,
          "to": null
        },
        "details": {
          "en": null,
          "np": null
        }
      }
    ]
  },
  {
    "calendarInfo": {
      "dates": {
        "bs": {
          "year": {
            "np": "२०२७",
            "en": "2027"
          },
          "month": {
            "np": "भाद्र",
            "code": {
              "np": "५",
              "en": "5"
            },
            "en": "Bhadra"
          },
          "day": {
            "np": "२५",
            "en": "25"
          },
          "full": {
            "np": "२०२७-५-२५",
            "en": "2027-5-25"
          }
        },
        "ad": {
          "year": {
            "np": "१९७०",
            "en": "1970"
          },
          "month": {
            "np": null,
            "code": {
              "np": null,
              "en": "9"
            },
            "en": "September"
          },
          "day": {
            "np": "१०",
            "en": "10"
          },
          "full": {
            "np": "१९७०-०९-१०",
            "en": "1970-9-10"
          }
        }
      },
      "days": {
        "dayOfWeek": {
          "np": "बिहिवार",
          "en": "Thursday"
        },
        "codes": {
          "np": null,
          "en": "5"
        }
      },
      "nepaliEra": {
        "sakSambat": {
          "np": null,
          "en": null
        },
        "nepalSambat": {
          "year": {
            "np": "१०९०",
            "en": "1090"
          },
          "month": {
            "np": null,
            "code": {
              "np": null,
              "en": null
            },
            "en": null
          }
        }
      }
    },
    "tithiDetails": null,
    "panchangaDetails": null,
    "hrituDetails": null,
    "auspiciousMoments": {
      "sahits": [],
      "muhurats": []
    },
    "eventDetails": [
      {
        "id": 5,
        "category": {
          "name": "Other",
          "id": 124049
        },
        "displayType": "Calendar Event",
        "title": {
          "np": "हिले जात्रा",
          "en": "Hile Jatra"
        },
        "isHoliday": false,
        "location": null,
        "timing": {
          "from": null,
          "to": null
        },
        "details": {
          "en": null,
          "np": null
        }
      },
      {
        "id": 5,
        "category": {
          "name": "Other",
          "id": 124400
        },
        "displayType": "Calendar Event",
        "title": {
          "np": "अदु:ख नवमी",
          "en": "Adukha Nawami Brat"
        },
        "isHoliday": false,
        "location": null,
        "timing": {
          "from": null,
          "to": null
        },
        "details": {
          "en": null,
          "np": null
        }
      }
    ]
  },
  {
    "calendarInfo": {
      "dates": {
        "bs": {
          "year": {
            "np": "२०२७",
            "en": "2027"
          },
          "month": {
            "np": "भाद्र",
            "code": {
              "np": "५",
              "en": "5"
            },
            "en": "Bhadra"
          },
          "day": {
            "np": "२६",
            "en": "26"
          },
          "full": {
            "np": "२०२७-५-२६",
            "en": "2027-5-26"
          }
        },
        "ad": {
          "year": {
            "np": "१९७०",
            "en": "1970"
          },
          "month": {
            "np": null,
            "code": {
              "np": null,
              "en": "9"
            },
            "en": "September"
          },
          "day": {
            "np": "११",
            "en": "11"
          },
          "full": {
            "np": "१९७०-०९-११",
            "en": "1970-9-11"
          }
        }
      },
      "days": {
        "dayOfWeek": {
          "np": "शुक्रवार",
          "en": "Friday"
        },
        "codes": {
          "np": null,
          "en": "6"
        }
      },
      "nepaliEra": {
        "sakSambat": {
          "np": null,
          "en": null
        },
        "nepalSambat": {
          "year": {
            "np": "१०९०",
            "en": "1090"
          },
          "month": {
            "np": null,
            "code": {
              "np": null,
              "en": null
            },
            "en": null
          }
        }
      }
    },
    "tithiDetails": null,
    "panchangaDetails": null,
    "hrituDetails": null,
    "auspiciousMoments": {
      "sahits": [],
      "muhurats": []
    },
    "eventDetails": [
      {
        "id": 5,
        "category": {
          "name": "Other",
          "id": 124399
        },
        "displayType": "Calendar Event",
        "title": {
          "np": "हरिपर्वर्तनि एकादशी व्रत",
          "en": "Hari Pariwartani Ekadashi Barta"
        },
        "isHoliday": false,
        "location": null,
        "timing": {
          "from": null,
          "to": null
        },
        "details": {
          "en": null,
          "np": null
        }
      }
    ]
  },
  {
    "calendarInfo": {
      "dates": {
        "bs": {
          "year": {
            "np": "२०२७",
            "en": "2027"
          },
          "month": {
            "np": "भाद्र",
            "code": {
              "np": "५",
              "en": "5"
            },
            "en": "Bhadra"
          },
          "day": {
            "np": "२७",
            "en": "27"
          },
          "full": {
            "np": "२०२७-५-२७",
            "en": "2027-5-27"
          }
        },
        "ad": {
          "year": {
            "np": "१९७०",
            "en": "1970"
          },
          "month": {
            "np": null,
            "code": {
              "np": null,
              "en": "9"
            },
            "en": "September"
          },
          "day": {
            "np": "१२",
            "en": "12"
          },
          "full": {
            "np": "१९७०-०९-१२",
            "en": "1970-9-12"
          }
        }
      },
      "days": {
        "dayOfWeek": {
          "np": "शनिवार",
          "en": "Saturday"
        },
        "codes": {
          "np": null,
          "en": "7"
        }
      },
      "nepaliEra": {
        "sakSambat": {
          "np": null,
          "en": null
        },
        "nepalSambat": {
          "year": {
            "np": "१०९०",
            "en": "1090"
          },
          "month": {
            "np": null,
            "code": {
              "np": null,
              "en": null
            },
            "en": null
          }
        }
      }
    },
    "tithiDetails": null,
    "panchangaDetails": null,
    "hrituDetails": null,
    "auspiciousMoments": {
      "sahits": [],
      "muhurats": []
    },
    "eventDetails": [
      {
        "id": 5,
        "category": {
          "name": "Other",
          "id": 124046
        },
        "displayType": "Calendar Event",
        "title": {
          "np": "ईन्द्रधोजोत्थान",
          "en": "Indradhoj utthan"
        },
        "isHoliday": false,
        "location": null,
        "timing": {
          "from": null,
          "to": null
        },
        "details": {
          "en": null,
          "np": null
        }
      },
      {
        "id": 5,
        "category": {
          "name": "Other",
          "id": 124398
        },
        "displayType": "Calendar Event",
        "title": {
          "np": "बामन द्वादशी",
          "en": "Baman Dwadashi"
        },
        "isHoliday": false,
        "location": null,
        "timing": {
          "from": null,
          "to": null
        },
        "details": {
          "en": null,
          "np": null
        }
      },
      {
        "id": 5,
        "category": {
          "name": "others",
          "id": 230939
        },
        "displayType": "Calendar Event",
        "title": {
          "np": "शनि प्रदोष व्रत",
          "en": "Shani Pradosh Brata"
        },
        "isHoliday": false,
        "location": null,
        "timing": {
          "from": null,
          "to": null
        },
        "details": {
          "en": null,
          "np": null
        }
      }
    ]
  },
  {
    "calendarInfo": {
      "dates": {
        "bs": {
          "year": {
            "np": "२०२७",
            "en": "2027"
          },
          "month": {
            "np": "भाद्र",
            "code": {
              "np": "५",
              "en": "5"
            },
            "en": "Bhadra"
          },
          "day": {
            "np": "२८",
            "en": "28"
          },
          "full": {
            "np": "२०२७-५-२८",
            "en": "2027-5-28"
          }
        },
        "ad": {
          "year": {
            "np": "१९७०",
            "en": "1970"
          },
          "month": {
            "np": null,
            "code": {
              "np": null,
              "en": "9"
            },
            "en": "September"
          },
          "day": {
            "np": "१३",
            "en": "13"
          },
          "full": {
            "np": "१९७०-०९-१३",
            "en": "1970-9-13"
          }
        }
      },
      "days": {
        "dayOfWeek": {
          "np": "आइतवार",
          "en": "Sunday"
        },
        "codes": {
          "np": null,
          "en": "1"
        }
      },
      "nepaliEra": {
        "sakSambat": {
          "np": null,
          "en": null
        },
        "nepalSambat": {
          "year": {
            "np": "१०९०",
            "en": "1090"
          },
          "month": {
            "np": null,
            "code": {
              "np": null,
              "en": null
            },
            "en": null
          }
        }
      }
    },
    "tithiDetails": null,
    "panchangaDetails": null,
    "hrituDetails": null,
    "auspiciousMoments": {
      "sahits": [],
      "muhurats": []
    },
    "eventDetails": []
  },
  {
    "calendarInfo": {
      "dates": {
        "bs": {
          "year": {
            "np": "२०२७",
            "en": "2027"
          },
          "month": {
            "np": "भाद्र",
            "code": {
              "np": "५",
              "en": "5"
            },
            "en": "Bhadra"
          },
          "day": {
            "np": "२९",
            "en": "29"
          },
          "full": {
            "np": "२०२७-५-२९",
            "en": "2027-5-29"
          }
        },
        "ad": {
          "year": {
            "np": "१९७०",
            "en": "1970"
          },
          "month": {
            "np": null,
            "code": {
              "np": null,
              "en": "9"
            },
            "en": "September"
          },
          "day": {
            "np": "१४",
            "en": "14"
          },
          "full": {
            "np": "१९७०-०९-१४",
            "en": "1970-9-14"
          }
        }
      },
      "days": {
        "dayOfWeek": {
          "np": "सोमवार",
          "en": "Monday"
        },
        "codes": {
          "np": null,
          "en": "2"
        }
      },
      "nepaliEra": {
        "sakSambat": {
          "np": null,
          "en": null
        },
        "nepalSambat": {
          "year": {
            "np": "१०९०",
            "en": "1090"
          },
          "month": {
            "np": null,
            "code": {
              "np": null,
              "en": null
            },
            "en": null
          }
        }
      }
    },
    "tithiDetails": null,
    "panchangaDetails": null,
    "hrituDetails": null,
    "auspiciousMoments": {
      "sahits": [],
      "muhurats": []
    },
    "eventDetails": [
      {
        "id": 5,
        "category": {
          "name": "Other",
          "id": 124258
        },
        "displayType": "Calendar Event",
        "title": {
          "np": "राष्ट्रि्य बाल दिवस",
          "en": "Childrens' Day"
        },
        "isHoliday": false,
        "location": null,
        "timing": {
          "from": null,
          "to": null
        },
        "details": {
          "en": null,
          "np": null
        }
      },
      {
        "id": 5,
        "category": {
          "name": "Other",
          "id": 124396
        },
        "displayType": "Calendar Event",
        "title": {
          "np": "इन्द्र जात्रा (काठमाण्डौ मात्र)",
          "en": "Indrajatra(Swachyaa) (Kumari-Bhairab Ganesh ko Raath Jaatraa)"
        },
        "isHoliday": false,
        "location": null,
        "timing": {
          "from": null,
          "to": null
        },
        "details": {
          "en": null,
          "np": null
        }
      },
      {
        "id": 5,
        "category": {
          "name": "Other",
          "id": 124397
        },
        "displayType": "Calendar Event",
        "title": {
          "np": "अनन्त चतुर्दशी",
          "en": "Ananta Chaturdashi Brat"
        },
        "isHoliday": false,
        "location": null,
        "timing": {
          "from": null,
          "to": null
        },
        "details": {
          "en": null,
          "np": null
        }
      }
    ]
  },
  {
    "calendarInfo": {
      "dates": {
        "bs": {
          "year": {
            "np": "२०२७",
            "en": "2027"
          },
          "month": {
            "np": "भाद्र",
            "code": {
              "np": "५",
              "en": "5"
            },
            "en": "Bhadra"
          },
          "day": {
            "np": "३०",
            "en": "30"
          },
          "full": {
            "np": "२०२७-५-३०",
            "en": "2027-5-30"
          }
        },
        "ad": {
          "year": {
            "np": "१९७०",
            "en": "1970"
          },
          "month": {
            "np": null,
            "code": {
              "np": null,
              "en": "9"
            },
            "en": "September"
          },
          "day": {
            "np": "१५",
            "en": "15"
          },
          "full": {
            "np": "१९७०-०९-१५",
            "en": "1970-9-15"
          }
        }
      },
      "days": {
        "dayOfWeek": {
          "np": "मङ्गलवार",
          "en": "Tuesday"
        },
        "codes": {
          "np": null,
          "en": "3"
        }
      },
      "nepaliEra": {
        "sakSambat": {
          "np": null,
          "en": null
        },
        "nepalSambat": {
          "year": {
            "np": "१०९०",
            "en": "1090"
          },
          "month": {
            "np": null,
            "code": {
              "np": null,
              "en": null
            },
            "en": null
          }
        }
      }
    },
    "tithiDetails": null,
    "panchangaDetails": null,
    "hrituDetails": null,
    "auspiciousMoments": {
      "sahits": [],
      "muhurats": []
    },
    "eventDetails": [
      {
        "id": 5,
        "category": {
          "name": "Other",
          "id": 124047
        },
        "displayType": "Calendar Event",
        "title": {
          "np": "ईन्द्रदह स्नान",
          "en": "Dahachowk(Kantipur) ma Indradaha Snan"
        },
        "isHoliday": false,
        "location": null,
        "timing": {
          "from": null,
          "to": null
        },
        "details": {
          "en": null,
          "np": null
        }
      },
      {
        "id": 5,
        "category": {
          "name": "Other",
          "id": 124101
        },
        "displayType": "Calendar Event",
        "title": {
          "np": "भक्तपुर सिद्धपोखरी मेला",
          "en": "Bhaktapur Siddha Pokhari Mela"
        },
        "isHoliday": false,
        "location": null,
        "timing": {
          "from": null,
          "to": null
        },
        "details": {
          "en": null,
          "np": null
        }
      },
      {
        "id": 5,
        "category": {
          "name": "Other",
          "id": 124260
        },
        "displayType": "Calendar Event",
        "title": {
          "np": "चेपाङ छोनाम पर्व",
          "en": "Chonamparwa (Chepang)"
        },
        "isHoliday": false,
        "location": null,
        "timing": {
          "from": null,
          "to": null
        },
        "details": {
          "en": null,
          "np": null
        }
      },
      {
        "id": 5,
        "category": {
          "name": "Other",
          "id": 124394
        },
        "displayType": "Calendar Event",
        "title": {
          "np": "सोर्ह श्राद्ध प्रारम्भ",
          "en": "Sorha Shradha Starts"
        },
        "isHoliday": false,
        "location": null,
        "timing": {
          "from": null,
          "to": null
        },
        "details": {
          "en": null,
          "np": null
        }
      },
      {
        "id": 6034,
        "category": {
          "name": "others",
          "id": 463032
        },
        "displayType": "Calendar Event",
        "title": {
          "np": "पुर्णिमा व्रत",
          "en": "Purnima Brata"
        },
        "isHoliday": false,
        "location": null,
        "timing": {
          "from": null,
          "to": null
        },
        "details": {
          "en": null,
          "np": null
        }
      }
    ]
  },
  {
    "calendarInfo": {
      "dates": {
        "bs": {
          "year": {
            "np": "२०२७",
            "en": "2027"
          },
          "month": {
            "np": "भाद्र",
            "code": {
              "np": "५",
              "en": "5"
            },
            "en": "Bhadra"
          },
          "day": {
            "np": "३१",
            "en": "31"
          },
          "full": {
            "np": "२०२७-५-३१",
            "en": "2027-5-31"
          }
        },
        "ad": {
          "year": {
            "np": "१९७०",
            "en": "1970"
          },
          "month": {
            "np": null,
            "code": {
              "np": null,
              "en": "9"
            },
            "en": "September"
          },
          "day": {
            "np": "१६",
            "en": "16"
          },
          "full": {
            "np": "१९७०-०९-१६",
            "en": "1970-9-16"
          }
        }
      },
      "days": {
        "dayOfWeek": {
          "np": "बुधवार",
          "en": "Wednesday"
        },
        "codes": {
          "np": null,
          "en": "4"
        }
      },
      "nepaliEra": {
        "sakSambat": {
          "np": null,
          "en": null
        },
        "nepalSambat": {
          "year": {
            "np": "१०९०",
            "en": "1090"
          },
          "month": {
            "np": null,
            "code": {
              "np": null,
              "en": null
            },
            "en": null
          }
        }
      }
    },
    "tithiDetails": null,
    "panchangaDetails": null,
    "hrituDetails": null,
    "auspiciousMoments": {
      "sahits": [],
      "muhurats": []
    },
    "eventDetails": [
      {
        "id": 5,
        "category": {
          "name": "Other",
          "id": 123982
        },
        "displayType": "Calendar Event",
        "title": {
          "np": "पुञ्चली भुजा",
          "en": "Punchali Bhuja"
        },
        "isHoliday": false,
        "location": null,
        "timing": {
          "from": null,
          "to": null
        },
        "details": {
          "en": null,
          "np": null
        }
      },
      {
        "id": 5,
        "category": {
          "name": "Other",
          "id": 124259
        },
        "displayType": "Calendar Event",
        "title": {
          "np": "प्रतिपदा श्राद्ध",
          "en": "Shraddha Start - Pratiprada Shraddha"
        },
        "isHoliday": false,
        "location": null,
        "timing": {
          "from": null,
          "to": null
        },
        "details": {
          "en": null,
          "np": null
        }
      }
    ]
  }
]